edgy.workflow-0.1.3-py3.4-nspkg.pth
edgy/workflow/__init__.py
edgy/workflow/constants.py
edgy/workflow/events.py
edgy/workflow/stateful.py
edgy/workflow/transition.py
edgy/workflow/utils.py
edgy/workflow/workflow.py
edgy/workflow/ext/__init__.py
edgy/workflow/ext/django_workflow/__init__.py
edgy/workflow/ext/django_workflow/forms.py
edgy/workflow/ext/django_workflow/models.py
edgy/workflow/ext/django_workflow/views.py
edgy.workflow-0.1.3.dist-info/DESCRIPTION.rst
edgy.workflow-0.1.3.dist-info/METADATA
edgy.workflow-0.1.3.dist-info/RECORD
edgy.workflow-0.1.3.dist-info/WHEEL
edgy.workflow-0.1.3.dist-info/metadata.json
edgy.workflow-0.1.3.dist-info/namespace_packages.txt
edgy.workflow-0.1.3.dist-info/top_level.txt
